mdmrgraph/__init__.py
mdmrgraph/graph.py
mdmrgraph/utils.py
mrsketch/__init__.py
mrsketch/benchmark.py
mrsketch/test.py
mrsketch-0.0.5.dist-info/LICENSE
mrsketch-0.0.5.dist-info/METADATA
mrsketch-0.0.5.dist-info/WHEEL
mrsketch-0.0.5.dist-info/top_level.txt
mrsketch-0.0.5.dist-info/RECORD
