Metadata-Version: 2.1
Name: mrsketch
Version: 0.0.5
Summary: Simple library for building multi-dimensional multi-resolution sketches
Home-page: https://github.com/Simonl07/mrsketch
Author: Simon Lu
Author-email: mlu18@dons.usfca.edu
License: UNKNOWN
Platform: UNKNOWN
Classifier: Development Status :: 1 - Planning
Classifier: Intended Audience :: Science/Research
Classifier: License :: OSI Approved :: MIT License
Classifier: Programming Language :: Python :: 3
